pyrankability/__init__.py
pyrankability/common.py
pyrankability/construct.py
pyrankability/features.py
pyrankability/plot.py
pyrankability/rank.py
pyrankability/search.py
pyrankability/utils.py
pyrankability-0.1.4.dist-info/LICENSE.txt
pyrankability-0.1.4.dist-info/METADATA
pyrankability-0.1.4.dist-info/WHEEL
pyrankability-0.1.4.dist-info/top_level.txt
pyrankability-0.1.4.dist-info/RECORD
