Metadata-Version: 2.1
Name: pyrankability
Version: 0.1.4
Summary: Ranking Python Library
Home-page: https://github.com/IGARDS/ranking_toolbox
Author: Paul Anderson, Tim Chartier, Amy Langville, Kathryn Behling
Author-email: pauleanderson@gmail.com
License: MIT
License-File: LICENSE.txt
Requires-Dist: gurobipy
Requires-Dist: matplotlib
Requires-Dist: pandas
Requires-Dist: networkx
Requires-Dist: altair
Requires-Dist: pygraphviz
Requires-Dist: scipy
Requires-Dist: sklearn
Requires-Dist: pytest
Requires-Dist: nx-altair
Requires-Dist: ipython
Requires-Dist: tqdm
